Metadata-Version: 1.0
Name: pdml2flow-elasticsearch
Version: 0.0
Summary: Saves pdml2flow output in elasticsearch
Home-page: https://github.com/Enteee/pdml2flow-elasticsearch
Author: Mischa Lehmann
Author-email: ducksource@duckpond.ch
License: Apache 2.0
Keywords: pdml2flow plugin elasticsearch
Platform: UNKNOWN
